CHANGES.txt
CONTRIBUTORS.txt
MANIFEST.in
README.rst
setup.py
collective/__init__.py
collective.maildigest.egg-info/PKG-INFO
collective.maildigest.egg-info/SOURCES.txt
collective.maildigest.egg-info/dependency_links.txt
collective.maildigest.egg-info/entry_points.txt
collective.maildigest.egg-info/namespace_packages.txt
collective.maildigest.egg-info/not-zip-safe
collective.maildigest.egg-info/requires.txt
collective.maildigest.egg-info/top_level.txt
collective/maildigest/__init__.py
collective/maildigest/configure.zcml
collective/maildigest/interfaces.py
collective/maildigest/minimal.zcml
collective/maildigest/rebuild_i18n.sh
collective/maildigest/skins.zcml
collective/maildigest/testing.py
collective/maildigest/tool.py
collective/maildigest/action/__init__.py
collective/maildigest/action/configure.zcml
collective/maildigest/action/digestemail-byfolder.zcml
collective/maildigest/action/digestemail_byfolder.py
collective/maildigest/action/log.py
collective/maildigest/action/log.zcml
collective/maildigest/action/templates/digestemail-byfolder.pt
collective/maildigest/activity/__init__.py
collective/maildigest/activity/add.py
collective/maildigest/activity/add.zcml
collective/maildigest/activity/configure.zcml
collective/maildigest/activity/delete.py
collective/maildigest/activity/delete.zcml
collective/maildigest/activity/modify.py
collective/maildigest/activity/modify.zcml
collective/maildigest/activity/move.py
collective/maildigest/activity/move.zcml
collective/maildigest/activity/publish.py
collective/maildigest/activity/publish.zcml
collective/maildigest/browser/__init__.py
collective/maildigest/browser/configure.zcml
collective/maildigest/browser/cron.py
collective/maildigest/browser/interfaces.py
collective/maildigest/browser/view.py
collective/maildigest/browser/viewlet.py
collective/maildigest/browser/templates/container-digest-icon.pt
collective/maildigest/browser/templates/container-digest-subscribe.pt
collective/maildigest/digestrules/__init__.py
collective/maildigest/digestrules/addedandmodifiedbysame.zcml
collective/maildigest/digestrules/addedandpublished.zcml
collective/maildigest/digestrules/addedandremoved.zcml
collective/maildigest/digestrules/configure.zcml
collective/maildigest/digestrules/modifiedandremoved.zcml
collective/maildigest/digestrules/rules.py
collective/maildigest/digestrules/sameeditor.zcml
